openap/__init__.py
openap/base.py
openap/contrail.py
openap/drag.py
openap/emission.py
openap/fuel.py
openap/gen.py
openap/kinematic.py
openap/mass.py
openap/phase.py
openap/prop.py
openap/thrust.py
openap/addon/__init__.py
openap/addon/bada3.py
openap/addon/bada4.py
openap/casadi/__init__.py
openap/casadi/aero_override.py
openap/casadi/numpy_override.py
openap/data/.gitignore
openap/data/LICENSE
openap/data/aircraft/_synonym.csv
openap/data/aircraft/a19n.yml
openap/data/aircraft/a20n.yml
openap/data/aircraft/a21n.yml
openap/data/aircraft/a318.yml
openap/data/aircraft/a319.yml
openap/data/aircraft/a320.yml
openap/data/aircraft/a321.yml
openap/data/aircraft/a332.yml
openap/data/aircraft/a333.yml
openap/data/aircraft/a343.yml
openap/data/aircraft/a359.yml
openap/data/aircraft/a388.yml
openap/data/aircraft/b37m.yml
openap/data/aircraft/b38m.yml
openap/data/aircraft/b39m.yml
openap/data/aircraft/b3xm.yml
openap/data/aircraft/b734.yml
openap/data/aircraft/b737.yml
openap/data/aircraft/b738.yml
openap/data/aircraft/b739.yml
openap/data/aircraft/b744.yml
openap/data/aircraft/b748.yml
openap/data/aircraft/b752.yml
openap/data/aircraft/b763.yml
openap/data/aircraft/b772.yml
openap/data/aircraft/b773.yml
openap/data/aircraft/b77w.yml
openap/data/aircraft/b788.yml
openap/data/aircraft/b789.yml
openap/data/aircraft/c550.yml
openap/data/aircraft/crj9.yml
openap/data/aircraft/e145.yml
openap/data/aircraft/e170.yml
openap/data/aircraft/e190.yml
openap/data/aircraft/e195.yml
openap/data/aircraft/e75l.yml
openap/data/aircraft/glf6.yml
openap/data/dragpolar/_synonym.csv
openap/data/dragpolar/a20n.yml
openap/data/dragpolar/a319.yml
openap/data/dragpolar/a320.yml
openap/data/dragpolar/a321.yml
openap/data/dragpolar/a332.yml
openap/data/dragpolar/a333.yml
openap/data/dragpolar/a343.yml
openap/data/dragpolar/a359.yml
openap/data/dragpolar/a388.yml
openap/data/dragpolar/b38m.yml
openap/data/dragpolar/b734.yml
openap/data/dragpolar/b737.yml
openap/data/dragpolar/b738.yml
openap-2.4.dist-info/METADATA
openap-2.4.dist-info/WHEEL
openap-2.4.dist-info/licenses/LICENSE
openap-2.4.dist-info/RECORD
