Metadata-Version: 2.4
Name: openap
Version: 2.4
Summary: Open Aircraft Performance Model (OpenAP) in Python
Project-URL: homepage, https://openap.dev
Project-URL: repository, https://github.com/junzis/openap
Project-URL: issues, https://github.com/junzis/openap/issues
Author-email: Junzi Sun <git@junzis.com>
License: GNU LGPL v3
License-File: LICENSE
Classifier: Development Status :: 4 - Beta
Classifier: Intended Audience :: Developers
Classifier: Intended Audience :: Information Technology
Classifier: Intended Audience :: Science/Research
Classifier: License :: OSI Approved :: GNU Lesser General Public License v3 (LGPLv3)
Classifier: Programming Language :: Python :: 3
Classifier: Topic :: Software Development :: Libraries :: Python Modules
Requires-Python: >=3.9
Requires-Dist: matplotlib>=3.1
Requires-Dist: numpy>=1.24
Requires-Dist: pandas>=1.2
Requires-Dist: pyyaml>=5.1
Requires-Dist: scipy>=1.7
